[
	{
		"name": "Helpful Fairy",
		"uniqueTo": "Kurai Sekai",
		"replaces": "Settler",
		"unitType": "Civilian",
		"movement": 2,
		"cost": 106,
		"uniques": ["Founds a new city <once>", "Can build [Land] improvements on tiles", "Ignores terrain cost", "Unbuildable"],
	},
	{
		"name": "Rumia",
		"uniqueTo": "Kurai Sekai",
		"unitType": "Dark Youkai",
		"movement": 2,
		"strength": 11,
		"cost": 120,
		"uniques": ["Can transform to [Orb of Darkness]", "Free [Tiny Rumia] appears <upon being defeated>"],
		"promotions": ["Darkness Manipulation"],
		"upgradesTo": "Danmaku Rumia",
	},
	{
		"name": "Orb of Darkness",
		"uniqueTo": "Kurai Sekai",
		"unitType": "Dark Youkai",
		"movement": 3,
		"strength": 15,
		"cost": 120,
		"uniques": ["Can transform to [Rumia]", "No Sight", "Invisible to non-adjacent units", "Cannot attack", "May enter foreign tiles without open borders", "Unbuildable", "Free [Tiny Rumia] appears <upon being defeated>"],
		"promotions": ["Darkness Manipulation"],
	},
	{
		"name": "Tiny Rumia",
		"uniqueTo": "Kurai Sekai",
		"unitType": "Dark Youkai",
		"movement": 2,
		"strength": 7,
		"cost": 120,
		"uniques": ["Can transform to [Dark Ball]", "Free [Tiny Rumia] appears <upon being defeated>"],
		"promotions": ["Darkness Manipulation"],
		"upgradesTo": "Danmaku Rumia",
	},
	{
		"name": "Dark Ball",
		"uniqueTo": "Kurai Sekai",
		"unitType": "Dark Youkai",
		"movement": 3,
		"strength": 11,
		"cost": 120,
		"uniques": ["Can transform to [Tiny Rumia]", "No Sight", "Invisible to non-adjacent units", "Cannot attack", "May enter foreign tiles without open borders", "Unbuildable", "Free [Tiny Rumia] appears <upon being defeated>"],
		"promotions": ["Darkness Manipulation"],
	},
	{
		"name": "Controlled Darkness",
		"uniqueTo": "Kurai Sekai",
		"unitType": "Dark Youkai",
		"movement": 3,
		"strength": 20,
		"cost": 250,
		"uniques": ["Can transform to [Danmaku Rumia]", "No Sight", "Invisible to non-adjacent units", "Cannot attack", "May enter foreign tiles without open borders", "Unbuildable", "Free [Tiny Rumia] appears <upon being defeated>"],
		"promotions": ["Darkness Manipulation"],
	},
	{
		"name": "Danmaku Rumia",
		"uniqueTo": "Kurai Sekai",
		"unitType": "Dark Youkai",
		"movement": 2,
		"strength": 14,
		"rangedStrength": 7,
		"cost": 250,
		"requiredTech": "Drama and Poetry",
		"uniques": ["Can transform to [Controlled Darkness]", "Must set up before ranged attack", "Unbuildable", "Free [Tiny Rumia] appears <upon being defeated>"],
		"promotions": ["Darkness Manipulation", "Danmaku"]
	},
]
